odoo/addons/auth_api_key_server_env/README.rst
odoo/addons/auth_api_key_server_env/__init__.py
odoo/addons/auth_api_key_server_env/__manifest__.py
odoo/addons/auth_api_key_server_env/i18n/auth_api_key_server_env.pot
odoo/addons/auth_api_key_server_env/i18n/it.po
odoo/addons/auth_api_key_server_env/models/__init__.py
odoo/addons/auth_api_key_server_env/models/auth_api_key.py
odoo/addons/auth_api_key_server_env/readme/CONTRIBUTORS.md
odoo/addons/auth_api_key_server_env/readme/CREDITS.md
odoo/addons/auth_api_key_server_env/readme/DESCRIPTION.md
odoo/addons/auth_api_key_server_env/static/description/icon.png
odoo/addons/auth_api_key_server_env/static/description/index.html
odoo/addons/auth_api_key_server_env/tests/__init__.py
odoo/addons/auth_api_key_server_env/tests/test_auth_api_key.py
odoo_addon_auth_api_key_server_env-18.0.1.0.0.3.dist-info/METADATA
odoo_addon_auth_api_key_server_env-18.0.1.0.0.3.dist-info/WHEEL
odoo_addon_auth_api_key_server_env-18.0.1.0.0.3.dist-info/top_level.txt
odoo_addon_auth_api_key_server_env-18.0.1.0.0.3.dist-info/RECORD
