Metadata-Version: 2.1
Name: odoo-addon-auth_api_key_server_env
Version: 18.0.1.0.0.3
Requires-Python: >=3.10
Requires-Dist: odoo-addon-auth_api_key==18.0.*
Requires-Dist: odoo-addon-server_environment==18.0.*
Requires-Dist: odoo==18.0.*
Summary: Configure api keys via server env. This can be very useful to avoid mixing your keys between your various environments when restoring databases. All you have to do is to add a new section to your configuration file according to the following convention:
Home-page: https://github.com/OCA/server-auth
License: LGPL-3
Author: Camptocamp,Odoo Community Association (OCA)
Author-email: support@odoo-community.org
Classifier: Programming Language :: Python
Classifier: Framework :: Odoo
Classifier: Framework :: Odoo :: 18.0
Classifier: License :: OSI Approved :: GNU Lesser General Public License v3 (LGPLv3)
Classifier: Development Status :: 5 - Production/Stable
